discordlite/__init__.py
discordlite/bot.py
discordlite/gateway.py
discordlite/http.py
discordlite/intents.py
discord_lite-0.1.0.dist-info/LICENSE
discord_lite-0.1.0.dist-info/METADATA
discord_lite-0.1.0.dist-info/WHEEL
discord_lite-0.1.0.dist-info/top_level.txt
discord_lite-0.1.0.dist-info/RECORD
