Metadata-Version: 2.1
Name: discord-lite
Version: 0.1.0
Summary: A lightweight Discord bot API library.
Author: rainy58
Author-email: yhg4908@kakao.com
Project-URL: Documentation, https://github.com/yhg4908/discord-lite/wiki
Project-URL: Issues, https://github.com/yhg4908/discord-lite/issues
Project-URL: Repository, https://github.com/yhg4908/discord-lite
Keywords: discord bot discordbot lite discord-lite lightweight http websockets api
Classifier: Development Status :: 2 - Pre-Alpha
Classifier: Intended Audience :: Developers
Classifier: License :: OSI Approved :: MIT License
Classifier: Programming Language :: Python :: 3
Classifier: Programming Language :: Python :: 3.7
Classifier: Programming Language :: Python :: 3.8
Classifier: Programming Language :: Python :: 3.9
Classifier: Programming Language :: Python :: 3.10
Classifier: Programming Language :: Python :: 3.11
Classifier: Programming Language :: Python :: 3.12
Classifier: Programming Language :: Python :: 3.13
Requires-Python: >=3.7
License-File: LICENSE
Requires-Dist: aiohttp >=3.11.11
Requires-Dist: websockets >=14.1
